piyon/__init__.py
piyon/main.py
piyon/template/.gitignore
piyon/template/setup.cfg
piyon/template/setup.py
piyon/template/src/__init__.py
piyon/template/tests/conftest.py
piyon-0.1.3.dist-info/METADATA
piyon-0.1.3.dist-info/RECORD
piyon-0.1.3.dist-info/WHEEL
piyon-0.1.3.dist-info/entry_points.txt
piyon-0.1.3.dist-info/top_level.txt
